{
    "durango": [
        "DUR-Agave-BR-A",
        "DUR-Agave-BR-B",
        "DUR-Agave-BR-C",
        "DUR-Agave-BR-D",
        "DUR-Agave-BR-E",
        "DUR-Agave-BR-F",
        "DUR-Boardroom",
        "DUR-Cactus",
        "DUR-Lantana-A",
        "DUR-Lantana-B",
        "DUR-Pre-Function",
        "DUR-Sauguaro",
        "DURANGO|ACS"
    ],
    "encore_main": [
        "Bach",
        "Beethoven",
        "Brahms",
        "Chopin",
        "Debussy",
        "Encore_B_1|2|3",
        "Encore_B_4|5|6",
        "Encore_B_7|5|8",
        "Encore_Ballroom_Hallway",
        "Handel",
        "Mozart",
        "Puccini",
        "Ravel",
        "Registration_5",
        "Registration_6",
        "Schubert",
        "Strauss",
        "Vivaldi"
    ],
    "gvr": [
        "ACS_GVR_Office",
        "GVR-8200Suite",
        "GVR-Boardroom",
        "GVR-Cielos",
        "GVR-Conv-Libraryrooms",
        "GVR-Convention",
        "GVR-DelRoomsandLuna",
        "GVR-ElViento",
        "GVR-EstanciaBallroom",
        "GVR-GrandBallroom",
        "GVR-GVR PRECON",
        "GVR-LaCascada",
        "GVR-LaSirena",
        "GVR-Tech-Office"
    ],
    "red_rock": [
        "ACS-RR-Office",
        "RR-Charleston_Ballroom",
        "RR-Pavilion_Ballroom",
        "RR-RedRock_Ballroom",
        "RR-Registration Area",
        "RR-Strip_Canyon_View",
        "RR-Summerlin_Ballroom",
        "RR-Tbones_Crimson",
        "RR_Veranda_Rooms"
    ],
    "stations_misc": [
        ".Boulder-Convention",
        ".FiestaHenderson-Convention",
        ".Palace-Convention",
        ".SantaFe-Convention",
        ".Sunset-Convention",
        ".Texas-Convention",
        "Boulder-Convention",
        "Palace-Convention",
        "SantaFe-Convention",
        "Sunset-Convention",
        "default"
    ],
    "wynn_expansion": [
        "Avignon",
        "Avize",
        "Bandol",
        "Bollinger",
        "Castillon",
        "Convention_Lounge",
        "Cristal_1|3",
        "Cristal_2|4",
        "Cristal_5|7",
        "Cristal_6|8",
        "Cristal_GreenRoom",
        "Cristal_Hallway",
        "Cristal_Terrace",
        "Epernay",
        "Fleurie",
        "Hermitage",
        "Krug",
        "Meursault",
        "Moet",
        "Mumm",
        "Musigny",
        "New_Wynn_BOH",
        "Pavillion/Garden",
        "Pomerol",
        "Registration_Desk_A",
        "Registration_Desk_B",
        "Reims",
        "Roederer",
        "Rotunda_Down",
        "Rotunda_Up",
        "Ruinart"
    ],
    "wynn_legacy": [
        "Alsace",
        "Chambertin",
        "Lafite_1|2|3",
        "Lafite_4|7|9",
        "Lafite_5|Stage",
        "Lafite_6|8",
        "Lafite_GreenRoom",
        "Lafite_Latour|Hallways",
        "Lafleur",
        "Latache",
        "Latour_1|4",
        "Latour_2|Stage",
        "Latour_3",
        "Latour_5|6|7",
        "Latour_GreenRoom",
        "Margaux",
        "Montrachet",
        "Mouton",
        "Palmer",
        "Petrus",
        "Registration_1",
        "Registration_2",
        "Registration_3",
        "Registration_4",
        "St_Julian",
        "St_Pierre",
        "Sunset_Terrace",
        "Wing-Lei"
    ],
    "wynn_misc": [
        "ACS-Office-TestAPs",
        "B10AP",
        "C4",
        "Catering_Office",
        "Delilah",
        "EncoreBusinessCenter",
        "Graton-Convention",
        "NoAuthApGroup",
        "WYNN|ENCORE-THEATRE",
        "WYNN|ENCORE-THEATRE|LOBBY",
        "WynnBusinessCenter",
        "XS_Nightclub",
        "default"
    ],
    "updater_enabled": true,
    "updater_metadata_url": "https://gist.githubusercontent.com/congiirepair/608d6a71617c2c8fba6dd2f7ee134dcc/raw/2af487571cc744ed62c5c4c20eeb27e3a0e1e2c7/version.txt",
    "updater_package_url": "https://github.com/congiirepair/ACS_Wynn_Builder/releases/download/1.0.4/ACS_Wynn_Builder_Update.zip",
    "updater_expected_sha256": "711b1f0eb54026f2cff413e14af2aab5d0b725aa64396e281cf6bdf9958d932b",
    "updater_allowed_hosts": [
        "gist.githubusercontent.com",
        "github.com",
        "githubusercontent.com",
        "objects.githubusercontent.com",
        "release-assets.githubusercontent.com"
    ]
}
